depht/__init__.py
depht/__main__.py
depht/data.py
depht/fetch_model.py
depht/classes/__init__.py
depht/classes/contig.py
depht/classes/file_translator.py
depht/classes/hhresult.py
depht/classes/progress.py
depht/classes/prophage.py
depht/classes/prophage_classifier.py
depht/functions/__init__.py
depht/functions/annotation.py
depht/functions/att.py
depht/functions/blastn.py
depht/functions/fasta.py
depht/functions/find_homologs.py
depht/functions/mmseqs.py
depht/functions/multiprocess.py
depht/functions/prophage_prediction.py
depht/functions/sliding_window.py
depht/functions/sniff_format.py
depht/functions/statistics.py
depht/functions/subprocess.py
depht/functions/visualization.py
depht_train/__init__.py
depht_train/__main__.py
depht_train/data.py
depht_train/run.py
depht_train/classes/__init__.py
depht_train/classes/database.py
depht_train/classes/kfold.py
depht_train/functions/__init__.py
depht_train/functions/blastdb.py
depht_train/functions/clustalo.py
depht_train/functions/config_handling.py
depht_train/functions/entrez.py
depht_train/functions/fileio.py
depht_train/functions/hhsuitedb.py
depht_train/functions/train_classifier.py
depht_train/pipelines/__init__.py
depht_train/pipelines/benchmark_output.py
depht_train/pipelines/build_HMM_db.py
depht_train/pipelines/build_reference_db.py
depht_train/pipelines/create_model.py
depht_train/pipelines/curate_gene_clusters.py
depht_train/pipelines/index_sequences.py
depht_train/pipelines/phamerate.py
depht_train/pipelines/plot_gene_density.py
depht_train/pipelines/pull_sequences.py
depht_train/pipelines/recut_fasta.py
depht_train/pipelines/screen_conserved_phams.py
depht_train/pipelines/train_model.py
depht-1.2.2.dist-info/METADATA
depht-1.2.2.dist-info/WHEEL
depht-1.2.2.dist-info/entry_points.txt
depht-1.2.2.dist-info/top_level.txt
depht-1.2.2.dist-info/RECORD
