Metadata-Version: 2.1
Name: depht
Version: 1.2.2
Summary: Discovery and Extraction of Phages Tool
Home-page: https://github.com/chg60/DEPhT
Author: Christian Gauthier
Author-email: chg60@pitt.edu
Classifier: Intended Audience :: Science/Research
Classifier: License :: OSI Approved :: GNU General Public License v3 (GPLv3)
Classifier: Operating System :: MacOS
Classifier: Operating System :: POSIX :: Linux
Classifier: Programming Language :: Python
Classifier: Programming Language :: Python :: 3
Classifier: Programming Language :: Python :: 3 :: Only
Classifier: Programming Language :: Python :: 3.8
Classifier: Programming Language :: Python :: 3.9
Classifier: Programming Language :: Python :: 3.10
Requires-Python: >=3.8
Requires-Dist: biopython >=1.78
Requires-Dist: bitarray ~=2.0.1
Requires-Dist: bokeh ~=2.4.2
Requires-Dist: dna-features-viewer ~=3.1.0
Requires-Dist: kaleido ~=0.2.1
Requires-Dist: matplotlib ~=3.4.1
Requires-Dist: numpy ~=1.22.3
Requires-Dist: pandas ~=1.4.2
Requires-Dist: phamclust ~=0.1.2
Requires-Dist: plotly ~=5.1.0
Requires-Dist: pretty-html-table ~=0.9.10
Requires-Dist: requests >=2.26.0
